allay/__init__.py
allay/json_parser.py
allay/parser.py
allay/plugin.py
allay-1.3.0.dist-info/LICENSE
allay-1.3.0.dist-info/WHEEL
allay-1.3.0.dist-info/METADATA
allay-1.3.0.dist-info/RECORD
