Metadata-Version: 2.1
Name: allay
Version: 1.3.0
Summary: A parser to convert a descriptive text format into minecraft text components
License: MIT
Author: DoubleFelix
Requires-Python: >=3.9,<4.0
Classifier: License :: OSI Approved :: MIT License
Classifier: Programming Language :: Python :: 3
Classifier: Programming Language :: Python :: 3.10
Classifier: Programming Language :: Python :: 3.9
Requires-Dist: tokenstream (>=1.4.1,<2.0.0)
